README.md
setup.py
wallet_parser/__init__.py
wallet_parser/bc_data_stream.py
wallet_parser/cli.py
wallet_parser/wallet_parser.py
wallet_parser.egg-info/PKG-INFO
wallet_parser.egg-info/SOURCES.txt
wallet_parser.egg-info/dependency_links.txt
wallet_parser.egg-info/entry_points.txt
wallet_parser.egg-info/requires.txt
wallet_parser.egg-info/top_level.txt