Metadata-Version: 1.0
Name: wallet-parser
Version: 0.0.1
Summary: parse wallet.dat file to get receiving addresses
Home-page: https://github.com/hausir/wallet-parser
Author: hausir
Author-email: hausir@icloud.com
License: MIT
Platform: any
